{"options":{},"indexes":[{"v":1,"key":{"_id":1},"name":"_id_","ns":"meteor.Discounts"},{"v":1,"key":{"shopId":1},"name":"c2_shopId","ns":"meteor.Discounts","background":true,"sparse":false},{"v":1,"key":{"discountMethod":1},"name":"c2_discountMethod","ns":"meteor.Discounts","background":true,"sparse":false},{"v":1,"key":{"calculation.method":1},"name":"c2_calculation.method","ns":"meteor.Discounts","background":true,"sparse":false},{"v":1,"key":{"transactions.cartId":1},"name":"c2_transactions.$.cartId","ns":"meteor.Discounts","background":true,"sparse":false},{"v":1,"key":{"transactions.userId":1},"name":"c2_transactions.$.userId","ns":"meteor.Discounts","background":true,"sparse":false}]}